episodes/__init__.py
episodes/module.s.HTML
episodes/Earth/current/__init__.py
episodes/Earth/current/status_current_1.py
episodes/Earth/distance/__init__.py
episodes/Earth/distance/days.py
episodes/Earth/distance/status_days_1.py
episodes/Earth/quarters/__init__.py
episodes/Earth/quarters/status_quarters_1.py
episodes/Earth/quarters/status_quarters_2.py
episodes/Earth/quarters/status_quarters_3.py
episodes/_clique/__init__.py
episodes/_clique/group/__init__.py
episodes/_status/establish.py
episodes/_status/status.proc.py
episodes/_status/DB/records.json
episodes-0.0.1.dist-info/METADATA
episodes-0.0.1.dist-info/WHEEL
episodes-0.0.1.dist-info/entry_points.txt
episodes-0.0.1.dist-info/top_level.txt
episodes-0.0.1.dist-info/RECORD
