Metadata-Version: 2.1
Name: episodes
Version: 0.0.1
Summary: rhythms and percussion
License: Mongo SSPL + GPL 3.0
Project-URL: GitLab, https://gitlab.com/offline-money/squash-1/episodes
Keywords: winks,hearts,orbits,ellipsis,calendar,agenda,priorities,schedule,rhythms
Requires-Python: >=3.8
Requires-Dist: onesie
Requires-Dist: click
Requires-Dist: flask
